the_spymaster_solvers_api/__init__.py
the_spymaster_solvers_api/client.py
the_spymaster_solvers_api/py.typed
the_spymaster_solvers_api/structs/__init__.py
the_spymaster_solvers_api/structs/base.py
the_spymaster_solvers_api/structs/errors.py
the_spymaster_solvers_api/structs/requests.py
the_spymaster_solvers_api/structs/responses.py
the_spymaster_solvers_api-3.1.0.dist-info/METADATA
the_spymaster_solvers_api-3.1.0.dist-info/WHEEL
the_spymaster_solvers_api-3.1.0.dist-info/RECORD
