Metadata-Version: 2.1
Name: the-spymaster-solvers-api
Version: 3.1.0
Summary: Python client implementation for The Spymaster Solvers HTTP backend.
Author: Asaf Kali
Author-email: asaf.kali@mail.huji.ac.il
Requires-Python: >=3.9,<4.0
Classifier: Programming Language :: Python :: 3
Classifier: Programming Language :: Python :: 3.9
Classifier: Programming Language :: Python :: 3.10
Classifier: Programming Language :: Python :: 3.11
Classifier: Programming Language :: Python :: 3.12
Requires-Dist: codenames (>=5.4,<6.0)
Requires-Dist: pydantic (>=2.8,<3.0)
Requires-Dist: requests (>=2.28,<3.0)
Requires-Dist: the-spymaster-util[clients] (>=4.0,<5.0)
Project-URL: Homepage, https://github.com/asaf-kali/the-spymaster-solvers
Project-URL: Issues, https://github.com/asaf-kali/the-spymaster-solvers/issues
Project-URL: Repository, https://github.com/asaf-kali/the-spymaster-solvers
